scout_mcp/__init__.py
scout_mcp/server.py
scout_mcp/tool_discovery.py
scout_mcp/tools/__init__.py
scout_mcp/tools/agent_tools.py
scout_mcp/tools/base_tool.py
scout_mcp/tools/ceregrep_query_tool.py
scout_mcp-0.2.3.dist-info/METADATA
scout_mcp-0.2.3.dist-info/WHEEL
scout_mcp-0.2.3.dist-info/entry_points.txt
scout_mcp-0.2.3.dist-info/RECORD
