Metadata-Version: 2.4
Name: scout-mcp
Version: 0.2.3
Summary: MCP server for Scout - exposes Scout query capabilities to other agents
Project-URL: Homepage, https://github.com/Swarm-Code/ceregrep-client
Project-URL: Documentation, https://github.com/Swarm-Code/ceregrep-client/blob/master/mcp-server/README.md
Project-URL: Repository, https://github.com/Swarm-Code/ceregrep-client
Project-URL: Issues, https://github.com/Swarm-Code/ceregrep-client/issues
Author: Swarm-Code
License-Expression: AGPL-3.0-or-later
Keywords: agent,cerebras,llm,mcp,model-context-protocol,scout,swarm
Classifier: Development Status :: 4 - Beta
Classifier: Intended Audience :: Developers
Classifier: License :: OSI Approved :: GNU Affero General Public License v3 or later (AGPLv3+)
Classifier: Programming Language :: Python :: 3
Classifier: Programming Language :: Python :: 3.10
Classifier: Programming Language :: Python :: 3.11
Classifier: Programming Language :: Python :: 3.12
Requires-Python: >=3.10
Requires-Dist: mcp>=1.0.0
